.DS_Store
cppyabm/__init__.py
cppyabm/binds.cpython-37m-darwin.so
scripts/batch_runner.py
cppyabm-1.0.21.dist-info/LICENSE
cppyabm-1.0.21.dist-info/METADATA
cppyabm-1.0.21.dist-info/WHEEL
cppyabm-1.0.21.dist-info/top_level.txt
cppyabm-1.0.21.dist-info/RECORD
