Metadata-Version: 2.1
Name: cppyabm
Version: 1.0.21
Summary: General-purpose agent-based modeling framework
Home-page: https://github.com/janursa/CppyABM
Author: Jalil Nourisa
Author-email: jalil.nourisa@gmail.com
License: UNKNOWN
Platform: UNKNOWN
Classifier: Programming Language :: Python :: 3
Classifier: License :: OSI Approved :: MIT License
Classifier: Operating System :: OS Independent
Requires-Python: >=3.6
License-File: LICENSE
